anywidget_test/__init__.py
anywidget_test/static/codicon-QHVHTGEQ.ttf
anywidget_test/static/widget.css
anywidget_test/static/widget.js
anywidget_test-0.0.1.dist-info/METADATA
anywidget_test-0.0.1.dist-info/WHEEL
anywidget_test-0.0.1.dist-info/RECORD
