Metadata-Version: 2.3
Name: anywidget_test
Version: 0.0.1
Requires-Dist: anywidget
Provides-Extra: dev
Requires-Dist: jupyterlab; extra == 'dev'
Requires-Dist: watchfiles; extra == 'dev'
